doc_tracker/__init__.py
doc_tracker/cli.py
doc_tracker/merger.py
doc_tracker/watcher.py
doc_tracker-1.0.0.dist-info/licenses/LICENSE
doc_tracker-1.0.0.dist-info/METADATA
doc_tracker-1.0.0.dist-info/WHEEL
doc_tracker-1.0.0.dist-info/entry_points.txt
doc_tracker-1.0.0.dist-info/top_level.txt
doc_tracker-1.0.0.dist-info/RECORD
