Metadata-Version: 2.4
Name: doc-tracker
Version: 1.0.0
Summary: Track and merge multiple documentation files into a single output file
Author-email: Djanghao <hstnzhang@gmail.com>
License-Expression: MIT
Classifier: Development Status :: 4 - Beta
Classifier: Intended Audience :: Developers
Classifier: Programming Language :: Python :: 3
Classifier: Programming Language :: Python :: 3.7
Classifier: Programming Language :: Python :: 3.8
Classifier: Programming Language :: Python :: 3.9
Classifier: Programming Language :: Python :: 3.10
Classifier: Programming Language :: Python :: 3.11
Classifier: Programming Language :: Python :: 3.12
Requires-Python: >=3.7
License-File: LICENSE
Requires-Dist: PyYAML>=6.0.0
Requires-Dist: watchdog>=3.0.0
Dynamic: license-file
